chessmate
