Metadata-Version: 2.1
Name: chessmate
Version: 1.0.5
Summary: Framework for defining and analyzing chess engines
Home-page: https://github.com/sansona/chessmate
Author: Jiaming Chen
Author-email: jiaming.justin.chen@gmail.com
License: GPL
Keywords: Chess chess
Platform: UNKNOWN
